spotifyunluck/__init__.py
spotifyunluck/__main__.py
spotifyunluck/main.py
spotifyunluck-0.0.3.dist-info/METADATA
spotifyunluck-0.0.3.dist-info/WHEEL
spotifyunluck-0.0.3.dist-info/top_level.txt
spotifyunluck-0.0.3.dist-info/RECORD
