Metadata-Version: 2.1
Name: spotifyunluck
Version: 0.0.3
Summary: Unluck Spotify Premium for free.
Author: Team Illusion
Classifier: Development Status :: 1 - Planning
Classifier: Intended Audience :: Developers
Classifier: Programming Language :: Python :: 3
Classifier: Operating System :: Unix
Classifier: Operating System :: MacOS :: MacOS X
Classifier: Operating System :: Microsoft :: Windows
Classifier: Operating System :: POSIX :: Linux
Classifier: Operating System :: Android
Requires-Dist: requests
Requires-Dist: illusioncolor
Requires-Dist: illusionanime
